fardes/__init__.py
fardes/parser.py
fardes/data/fardes.tf.yaml
fardes-1.2.dist-info/AUTHORS.txt
fardes-1.2.dist-info/LICENSE.txt
fardes-1.2.dist-info/METADATA
fardes-1.2.dist-info/WHEEL
fardes-1.2.dist-info/top_level.txt
fardes-1.2.dist-info/RECORD
